hue_shift/__init__.py
hue_shift/main.py
hue_shift-1.1.dist-info/METADATA
hue_shift-1.1.dist-info/WHEEL
hue_shift-1.1.dist-info/top_level.txt
hue_shift-1.1.dist-info/RECORD
