Metadata-Version: 2.1
Name: hue-shift
Version: 1.1
Summary: A simple script for generating ~16 million colors without dependencies
Home-page: https://github.com/EchterAlsFake/hue_shift
Author: EchterAlsFake | Johannes Habel
Author-email: EchterAlsFake@proton.me
License: LGPLv3
Classifier: License :: OSI Approved :: GNU Lesser General Public License v3 (LGPLv3)
Classifier: Programming Language :: Python
